mozshellutil/__init__.py
mozshellutil/shellutil.py
mozshellutil-1.0.0.dist-info/METADATA
mozshellutil-1.0.0.dist-info/WHEEL
mozshellutil-1.0.0.dist-info/top_level.txt
mozshellutil-1.0.0.dist-info/RECORD
